nnabla_rl/__init__.py
nnabla_rl/algorithm.py
nnabla_rl/configuration.py
nnabla_rl/environment_explorer.py
nnabla_rl/exceptions.py
nnabla_rl/functions.py
nnabla_rl/hook.py
nnabla_rl/initializers.py
nnabla_rl/logger.py
nnabla_rl/parametric_functions.py
nnabla_rl/random.py
nnabla_rl/replay_buffer.py
nnabla_rl/scopes.py
nnabla_rl/typing.py
nnabla_rl/writer.py
nnabla_rl/algorithms/__init__.py
nnabla_rl/algorithms/a2c.py
nnabla_rl/algorithms/amp.py
nnabla_rl/algorithms/atrpo.py
nnabla_rl/algorithms/bcq.py
nnabla_rl/algorithms/bear.py
nnabla_rl/algorithms/categorical_ddqn.py
nnabla_rl/algorithms/categorical_dqn.py
nnabla_rl/algorithms/common_utils.py
nnabla_rl/algorithms/ddp.py
nnabla_rl/algorithms/ddpg.py
nnabla_rl/algorithms/ddqn.py
nnabla_rl/algorithms/decision_transformer.py
nnabla_rl/algorithms/demme_sac.py
nnabla_rl/algorithms/dqn.py
nnabla_rl/algorithms/drqn.py
nnabla_rl/algorithms/dummy.py
nnabla_rl/algorithms/gail.py
nnabla_rl/algorithms/her.py
nnabla_rl/algorithms/hyar.py
nnabla_rl/algorithms/icml2015_trpo.py
nnabla_rl/algorithms/icml2018_sac.py
nnabla_rl/algorithms/icra2018_qtopt.py
nnabla_rl/algorithms/ilqr.py
nnabla_rl/algorithms/iql.py
nnabla_rl/algorithms/iqn.py
nnabla_rl/algorithms/lqr.py
nnabla_rl/algorithms/mme_sac.py
nnabla_rl/algorithms/mppi.py
nnabla_rl/algorithms/munchausen_dqn.py
nnabla_rl/algorithms/munchausen_iqn.py
nnabla_rl/algorithms/option_critic.py
nnabla_rl/algorithms/ppo.py
nnabla_rl/algorithms/qrdqn.py
nnabla_rl/algorithms/qrsac.py
nnabla_rl/algorithms/rainbow.py
nnabla_rl/algorithms/redq.py
nnabla_rl/algorithms/reinforce.py
nnabla_rl/algorithms/sac.py
nnabla_rl/algorithms/sacd.py
nnabla_rl/algorithms/srsac.py
nnabla_rl/algorithms/td3.py
nnabla_rl/algorithms/trpo.py
nnabla_rl/algorithms/xql.py
nnabla_rl/builders/__init__.py
nnabla_rl/builders/explorer_builder.py
nnabla_rl/builders/lr_scheduler_builder.py
nnabla_rl/builders/model_builder.py
nnabla_rl/builders/preprocessor_builder.py
nnabla_rl/builders/replay_buffer_builder.py
nnabla_rl-0.16.0.dist-info/LICENSE
nnabla_rl-0.16.0.dist-info/METADATA
nnabla_rl-0.16.0.dist-info/WHEEL
nnabla_rl-0.16.0.dist-info/top_level.txt
nnabla_rl-0.16.0.dist-info/RECORD
