Metadata-Version: 2.1
Name: nnabla_rl
Version: 0.16.0
Summary: Deep reinforcement learning library built on top of Neural Network Libraries
Author: Sony Group Corporation
Maintainer: Yu Ishihara, Shunichi Sekiguchi, Takayoshi Takayanagi
License: 
Project-URL: Homepage, https://github.com/sony/nnabla-rl
Project-URL: Repository, https://github.com/sony/nnabla-rl
Project-URL: Documentation, https://nnabla-rl.readthedocs.io/en/latest/
Keywords: deep learning,artificial intelligence,machine learning,neural network
Classifier: Development Status :: 5 - Production/Stable
Classifier: Intended Audience :: Developers
Classifier: Intended Audience :: Education
Classifier: Intended Audience :: Science/Research
Classifier: Topic :: Scientific/Engineering
Classifier: Topic :: Scientific/Engineering :: Artificial Intelligence
Classifier: License :: OSI Approved :: Apache Software License
Classifier: Programming Language :: Python :: 3
Classifier: Programming Language :: Python :: 3.8
Classifier: Programming Language :: Python :: 3.9
Classifier: Programming Language :: Python :: 3.10
Classifier: Operating System :: POSIX :: Linux
Requires-Python: >=3.8
License-File: LICENSE
Requires-Dist: nnabla!=1.18.0,>=1.17
Requires-Dist: numpy>=1.17
Requires-Dist: gym<0.26.0
Requires-Dist: opencv-python
Requires-Dist: packaging
Requires-Dist: tqdm
Requires-Dist: gymnasium
Provides-Extra: deploy
Requires-Dist: setuptools>=61.0.0; extra == "deploy"
Requires-Dist: wheel; extra == "deploy"
Requires-Dist: build; extra == "deploy"
Requires-Dist: twine; extra == "deploy"
Provides-Extra: dev
Requires-Dist: flake8; extra == "dev"
Requires-Dist: pylint; extra == "dev"
Requires-Dist: pytest; extra == "dev"
Requires-Dist: pytest-cov; extra == "dev"
Requires-Dist: mypy!=1.11.0; extra == "dev"
Requires-Dist: typing-extensions; extra == "dev"
Requires-Dist: isort>5.0.0; extra == "dev"
Requires-Dist: black; extra == "dev"
Requires-Dist: docformatter; extra == "dev"
Provides-Extra: doc
Requires-Dist: sphinx; extra == "doc"
Requires-Dist: sphinx-rtd-theme; extra == "doc"
Provides-Extra: render
Requires-Dist: pyglet>=1.4.0; extra == "render"
Provides-Extra: test
Requires-Dist: pytest; extra == "test"
Requires-Dist: pytest-cov; extra == "test"
Requires-Dist: mock; extra == "test"
